Supysonic-0.7.9.data/data/share/man/man1/supysonic-cli-folder.1
Supysonic-0.7.9.data/data/share/man/man1/supysonic-cli-user.1
Supysonic-0.7.9.data/data/share/man/man1/supysonic-cli.1
Supysonic-0.7.9.data/data/share/man/man1/supysonic-daemon.1
Supysonic-0.7.9.data/data/share/man/man1/supysonic-server.1
supysonic/__init__.py
supysonic/cache.py
supysonic/cli.py
supysonic/config.py
supysonic/covers.py
supysonic/db.py
supysonic/jukebox.py
supysonic/lastfm.py
supysonic/listenbrainz.py
supysonic/scanner.py
supysonic/utils.py
supysonic/watcher.py
supysonic/web.py
supysonic/api/__init__.py
supysonic/api/albums_songs.py
supysonic/api/annotation.py
supysonic/api/browse.py
supysonic/api/chat.py
supysonic/api/errors.py
supysonic/api/exceptions.py
supysonic/api/formatters.py
supysonic/api/jukebox.py
supysonic/api/media.py
supysonic/api/playlists.py
supysonic/api/radio.py
supysonic/api/scan.py
supysonic/api/search.py
supysonic/api/system.py
supysonic/api/unsupported.py
supysonic/api/user.py
supysonic/daemon/__init__.py
supysonic/daemon/__main__.py
supysonic/daemon/client.py
supysonic/daemon/exceptions.py
supysonic/daemon/server.py
supysonic/frontend/__init__.py
supysonic/frontend/folder.py
supysonic/frontend/playlist.py
supysonic/frontend/user.py
supysonic/managers/__init__.py
supysonic/managers/folder.py
supysonic/managers/user.py
supysonic/schema/mysql.sql
supysonic/schema/postgres.sql
supysonic/schema/sqlite.sql
supysonic/schema/migration/mysql/20161030.sql
supysonic/schema/migration/mysql/20171022.sql
supysonic/schema/migration/mysql/20171230.py
supysonic/schema/migration/mysql/20180221.sql
supysonic/schema/migration/mysql/20180317.sql
supysonic/schema/migration/mysql/20180521.sql
supysonic/schema/migration/mysql/20181010.sql
supysonic/schema/migration/mysql/20190324.sql
supysonic/schema/migration/mysql/20190518.sql
supysonic/schema/migration/mysql/20190915.sql
supysonic/schema/migration/mysql/20190921.sql
supysonic/schema/migration/mysql/20200607.sql
Supysonic-0.7.9.dist-info/LICENSE
Supysonic-0.7.9.dist-info/METADATA
Supysonic-0.7.9.dist-info/WHEEL
Supysonic-0.7.9.dist-info/entry_points.txt
Supysonic-0.7.9.dist-info/top_level.txt
Supysonic-0.7.9.dist-info/RECORD
