Metadata-Version: 2.1
Name: Supysonic
Version: 0.7.9
Summary: Python implementation of the Subsonic server API
Home-page: https://supysonic.readthedocs.io
Download-URL: https://github.com/spl0k/supysonic
Author: Alban Féron
Author-email: alban.feron@gmail.com
License: GNU AGPLv3
Keywords: subsonic,music,server
Classifier: Development Status :: 3 - Alpha
Classifier: Environment :: Console
Classifier: Environment :: Web Environment
Classifier: Framework :: Flask
Classifier: Intended Audience :: End Users/Desktop
Classifier: Intended Audience :: System Administrators
Classifier: License :: OSI Approved :: GNU Affero General Public License v3
Classifier: Programming Language :: Python :: 3
Classifier: Programming Language :: Python :: 3.7
Classifier: Programming Language :: Python :: 3.8
Classifier: Programming Language :: Python :: 3.9
Classifier: Programming Language :: Python :: 3.10
Classifier: Programming Language :: Python :: 3.11
Classifier: Programming Language :: Python :: 3.12
Classifier: Topic :: Multimedia :: Sound/Audio
Requires-Python: >=3.7
License-File: LICENSE
Requires-Dist: click
Requires-Dist: flask>=0.11
Requires-Dist: peewee
Requires-Dist: Pillow>=9.1.0
Requires-Dist: requests>=1.0.0
Requires-Dist: mediafile
Requires-Dist: watchdog>=0.8.0
Requires-Dist: zipstream-ng<2.0.0,>=1.1.0
